fullcontact/__about__.py
fullcontact/__init__.py
fullcontact/exceptions.py
fullcontact/api/__init__.py
fullcontact/api/audience_api.py
fullcontact/api/company_api.py
fullcontact/api/permission_api.py
fullcontact/api/person_api.py
fullcontact/api/resolve_api.py
fullcontact/api/tags_api.py
fullcontact/api/verify_api.py
fullcontact/api/base/__init__.py
fullcontact/api/base/base_api.py
fullcontact/api/base/enrich_base_api.py
fullcontact/api/base/tags_base_api.py
fullcontact/config/__init__.py
fullcontact/config/client_config.py
fullcontact/response/__init__.py
fullcontact/response/audience_response.py
fullcontact/response/company_response.py
fullcontact/response/permission_response.py
fullcontact/response/person_response.py
fullcontact/response/resolve_response.py
fullcontact/response/tags_response.py
fullcontact/response/verify_response.py
fullcontact/response/base/__init__.py
fullcontact/response/base/base.py
fullcontact/response/base/enrich_base.py
fullcontact/response/base/tags_base.py
fullcontact/schema/__init__.py
fullcontact/schema/audience_schema.py
fullcontact/schema/company_schema.py
fullcontact/schema/permission_schema.py
fullcontact/schema/person_schema.py
fullcontact/schema/resolve_schema.py
fullcontact/schema/tags_schema.py
fullcontact/schema/verify_schema.py
fullcontact/schema/base/__init__.py
fullcontact/schema/base/schema_base.py
tests/resources/__init__.py
tests/utils/__init__.py
tests/utils/error_messages.py
tests/utils/mock_request.py
tests/utils/mock_response.py
python_fullcontact-4.0.0.dist-info/LICENSE
python_fullcontact-4.0.0.dist-info/METADATA
python_fullcontact-4.0.0.dist-info/WHEEL
python_fullcontact-4.0.0.dist-info/top_level.txt
python_fullcontact-4.0.0.dist-info/RECORD
