Metadata-Version: 2.1
Name: python-fullcontact
Version: 4.0.0
Summary: Client library for FullContact V3 Enrich and Resolve APIs
Home-page: https://github.com/fullcontact/fullcontact-python-client
Author: FullContact
Author-email: pypy@fullcontact.com
License: Apache License, Version 2.0
Requires-Python: ~=3.5
License-File: LICENSE
Requires-Dist: requests (<3,>=2.23.0)
Requires-Dist: urllib3 (<2,>=1.25.7)
Provides-Extra: develop
Requires-Dist: pytest (==5.4.1) ; extra == 'develop'
